LICENSE
README.md
setup.py
HydraGNN.egg-info/PKG-INFO
HydraGNN.egg-info/SOURCES.txt
HydraGNN.egg-info/dependency_links.txt
HydraGNN.egg-info/requires.txt
HydraGNN.egg-info/top_level.txt
hydragnn/__init__.py
hydragnn/run_prediction.py
hydragnn/run_training.py
hydragnn/models/Base.py
hydragnn/models/CGCNNStack.py
hydragnn/models/DIMEStack.py
hydragnn/models/EGCLStack.py
hydragnn/models/GATStack.py
hydragnn/models/GINStack.py
hydragnn/models/MFCStack.py
hydragnn/models/PNAStack.py
hydragnn/models/SAGEStack.py
hydragnn/models/SCFStack.py
hydragnn/models/__init__.py
hydragnn/models/create.py
hydragnn/postprocess/__init__.py
hydragnn/postprocess/postprocess.py
hydragnn/postprocess/visualizer.py
hydragnn/preprocess/__init__.py
hydragnn/preprocess/cfg_raw_dataset_loader.py
hydragnn/preprocess/compositional_data_splitting.py
hydragnn/preprocess/dataset_descriptors.py
hydragnn/preprocess/load_data.py
hydragnn/preprocess/lsms_raw_dataset_loader.py
hydragnn/preprocess/raw_dataset_loader.py
hydragnn/preprocess/serialized_dataset_loader.py
hydragnn/preprocess/utils.py
hydragnn/train/__init__.py
hydragnn/train/train_validate_test.py
hydragnn/utils/__init__.py
hydragnn/utils/abstractbasedataset.py
hydragnn/utils/abstractrawdataset.py
hydragnn/utils/adiosdataset.py
hydragnn/utils/atomicdescriptors.py
hydragnn/utils/cfgdataset.py
hydragnn/utils/config_utils.py
hydragnn/utils/distdataset.py
hydragnn/utils/distributed.py
hydragnn/utils/gptl4py_dummy.py
hydragnn/utils/lsmsdataset.py
hydragnn/utils/model.py
hydragnn/utils/optimizer.py
hydragnn/utils/pickledataset.py
hydragnn/utils/print_utils.py
hydragnn/utils/profile.py
hydragnn/utils/serializeddataset.py
hydragnn/utils/smiles_utils.py
hydragnn/utils/time_utils.py
hydragnn/utils/tracer.py
hydragnn/utils/xyzdataset.py
tests/__init__.py
tests/deterministic_graph_data.py
tests/test_atomicdescriptors.py
tests/test_config.py
tests/test_datasetclass_inheritance.py
tests/test_enthalpy.py
tests/test_examples.py
tests/test_graphs.py
tests/test_loss_and_activation_functions.py
tests/test_model_loadpred.py
tests/test_optimizer.py
tests/test_periodic_boundary_conditions.py
