Metadata-Version: 2.1
Name: HydraGNN
Version: 3.0
Summary: Distributed PyTorch implementation of multi-headed graph convolutional neural networks
Home-page: https://github.com/ORNL/HydraGNN
Author: Massimiliano Lupo Pasini, Samuel Temple Reeve, Pei Zhang, Jong Youl Choi
Author-email: lupopasinim@ornl.gov
License: BSD-3
Provides-Extra: test
License-File: LICENSE
